clipster/__init__.py
clipster/api.py
clipster/clipster.py
clipster/config.py
clipster/crypt.py
clipster/gui.py
clipster/log_config.py
clipster_desktop-0.4.5.data/scripts/clipster_disable.sh
clipster_desktop-0.4.5.data/scripts/clipster_enable.sh
clipster_desktop-0.4.5.dist-info/LICENSE
clipster_desktop-0.4.5.dist-info/METADATA
clipster_desktop-0.4.5.dist-info/WHEEL
clipster_desktop-0.4.5.dist-info/entry_points.txt
clipster_desktop-0.4.5.dist-info/top_level.txt
clipster_desktop-0.4.5.dist-info/RECORD
