Metadata-Version: 2.1
Name: clipster-desktop
Version: 0.4.5
Summary: Multi Platform Cloud Clipboard - Desktop Client
Home-page: http://github.com/mc51/Clipster-Desktop
Author: MC51
Author-email: mc@data-dive.com
License: MIT
Project-URL: Bug Reports, https://github.com/mc51/Clipster-Desktop/issues
Project-URL: Source, https://github.com/mc51/Clipster-Desktop/
Project-URL: Developer Website, https://data-dive.com
Keywords: clipster,clipboard,cryptography,secure,copy&paste,cloud,clipboard manager,data dive
Platform: UNKNOWN
Classifier: Topic :: Desktop Environment
Classifier: Topic :: Internet :: WWW/HTTP
Classifier: Topic :: Utilities
Classifier: Topic :: System
Classifier: Topic :: Security :: Cryptography
Classifier: Development Status :: 4 - Beta
Classifier: Environment :: MacOS X
Classifier: Environment :: X11 Applications
Classifier: Environment :: Win32 (MS Windows)
Classifier: Intended Audience :: Developers
Classifier: Intended Audience :: End Users/Desktop
Classifier: License :: OSI Approved :: MIT License
Classifier: Programming Language :: Python :: 3
Classifier: Operating System :: OS Independent
Requires-Python: >=3.6
Requires-Dist: requests
Requires-Dist: pyperclip
Requires-Dist: PySide2
Requires-Dist: PySimpleGUI
Requires-Dist: PySimpleGUIQt
Requires-Dist: cryptography
